imageatm/__init__.py
imageatm/client/__init__.py
imageatm/client/client.py
imageatm/client/commands.py
imageatm/client/config.py
imageatm/components/__init__.py
imageatm/components/cloud.py
imageatm/components/dataprep.py
imageatm/components/evaluation.py
imageatm/components/training.py
imageatm/handlers/__init__.py
imageatm/handlers/data_generator.py
imageatm/handlers/image_classifier.py
imageatm/notebooks/__init__.py
imageatm/notebooks/evaluation_template.ipynb
imageatm/notebooks/tex_templates/evaluation_report.tplx
imageatm/scripts/__init__.py
imageatm/scripts/run_cloud.py
imageatm/scripts/run_dataprep.py
imageatm/scripts/run_evaluation.py
imageatm/scripts/run_training.py
imageatm/scripts/run_training_cloud.py
imageatm/utils/__init__.py
imageatm/utils/images.py
imageatm/utils/io.py
imageatm/utils/logger.py
imageatm/utils/process.py
imageatm/utils/tf_keras.py
imageatm-0.1.1.dist-info/LICENSE
imageatm-0.1.1.dist-info/METADATA
imageatm-0.1.1.dist-info/WHEEL
imageatm-0.1.1.dist-info/entry_points.txt
imageatm-0.1.1.dist-info/top_level.txt
imageatm-0.1.1.dist-info/RECORD
